setup.cfg
setup.py
etc/__about__.py
etc/__init__.py
etc/adapter.py
etc/client.py
etc/errors.py
etc/helpers.py
etc/results.py
etc/sugar.py
etc.egg-info/PKG-INFO
etc.egg-info/SOURCES.txt
etc.egg-info/dependency_links.txt
etc.egg-info/not-zip-safe
etc.egg-info/requires.txt
etc.egg-info/top_level.txt
etc/adapters/__init__.py
etc/adapters/etcd.py
etc/adapters/mock.py